langscript/__init__.py
langscript/core.py
langscript-0.0.1.dist-info/LICENSE
langscript-0.0.1.dist-info/METADATA
langscript-0.0.1.dist-info/WHEEL
langscript-0.0.1.dist-info/RECORD
